{
  "fetched_at": "2026-07-21T20:54:26Z",
  "data": {
    "period": "1h",
    "liveNow": 1,
    "overview": {
      "unique_users": 5,
      "total_tunes": 19,
      "total_watch_min": 1.6,
      "avg_duration_sec": 4.9
    },
    "channelLeaderboard": [
      {
        "ch": 40,
        "name": "Aaj Tak HD",
        "cat": "News",
        "lang": "Hindi",
        "tunes": 1,
        "unique_users": 1,
        "watch_min": 0.5
      },
      {
        "ch": 193,
        "name": "Sana TV",
        "cat": "Entertainment",
        "lang": "Hindi",
        "tunes": 1,
        "unique_users": 1,
        "watch_min": 0.1
      },
      {
        "ch": 180,
        "name": "PTC Punjabi Gold",
        "cat": "Entertainment",
        "lang": "Punjabi",
        "tunes": 1,
        "unique_users": 1,
        "watch_min": 0.1
      },
      {
        "ch": 122,
        "name": "GTC Punjabi",
        "cat": "Entertainment",
        "lang": "Punjabi",
        "tunes": 1,
        "unique_users": 1,
        "watch_min": 0.1
      },
      {
        "ch": 26,
        "name": "Shemaroo Marathi Bana",
        "cat": "Movies",
        "lang": "Marathi",
        "tunes": 1,
        "unique_users": 1,
        "watch_min": 0.1
      },
      {
        "ch": 24,
        "name": "Bhojpuri Cinema",
        "cat": "Movies",
        "lang": "Bhojpuri",
        "tunes": 2,
        "unique_users": 2,
        "watch_min": 0.1
      },
      {
        "ch": 12,
        "name": "Abzy Movies",
        "cat": "Entertainment",
        "lang": "Hindi",
        "tunes": 1,
        "unique_users": 1,
        "watch_min": 0.1
      },
      {
        "ch": 6,
        "name": "Zee Dil Se",
        "cat": "Entertainment",
        "lang": "Hindi",
        "tunes": 1,
        "unique_users": 1,
        "watch_min": 0.1
      },
      {
        "ch": 3,
        "name": "Dangal 2",
        "cat": "Entertainment",
        "lang": "Hindi",
        "tunes": 1,
        "unique_users": 1,
        "watch_min": 0.1
      },
      {
        "ch": 226,
        "name": "Times Now Navbharat",
        "cat": "News",
        "lang": "Hindi",
        "tunes": 1,
        "unique_users": 1,
        "watch_min": 0
      },
      {
        "ch": 208,
        "name": "South Station",
        "cat": "Movies",
        "lang": "Hindi",
        "tunes": 1,
        "unique_users": 1,
        "watch_min": 0
      },
      {
        "ch": 16,
        "name": "Travelxp HD",
        "cat": "Entertainment",
        "lang": "English",
        "tunes": 1,
        "unique_users": 1,
        "watch_min": 0
      },
      {
        "ch": 15,
        "name": "NDTV Good Times",
        "cat": "Entertainment",
        "lang": "English",
        "tunes": 1,
        "unique_users": 1,
        "watch_min": 0
      },
      {
        "ch": 11,
        "name": "Shubh Cinema",
        "cat": "Entertainment",
        "lang": "Hindi",
        "tunes": 1,
        "unique_users": 1,
        "watch_min": 0
      },
      {
        "ch": 10,
        "name": "History TV18 HD",
        "cat": "Entertainment",
        "lang": "Hindi",
        "tunes": 1,
        "unique_users": 1,
        "watch_min": 0
      },
      {
        "ch": 7,
        "name": "Zee Horror Nights",
        "cat": "Entertainment",
        "lang": "Hindi",
        "tunes": 1,
        "unique_users": 1,
        "watch_min": 0
      },
      {
        "ch": 4,
        "name": "Epic TV",
        "cat": "Entertainment",
        "lang": "Hindi",
        "tunes": 1,
        "unique_users": 1,
        "watch_min": 0
      },
      {
        "ch": 2,
        "name": "Dangal TV",
        "cat": "Entertainment",
        "lang": "Hindi",
        "tunes": 1,
        "unique_users": 1,
        "watch_min": 0
      }
    ],
    "categoryBreakdown": [
      {
        "cat": "Entertainment",
        "tunes": 13,
        "unique_users": 1,
        "watch_min": 0.7
      },
      {
        "cat": "News",
        "tunes": 2,
        "unique_users": 2,
        "watch_min": 0.6
      },
      {
        "cat": "Movies",
        "tunes": 4,
        "unique_users": 2,
        "watch_min": 0.3
      }
    ],
    "languageBreakdown": [
      {
        "lang": "Hindi",
        "tunes": 12,
        "unique_users": 4,
        "watch_min": 1.1
      },
      {
        "lang": "Punjabi",
        "tunes": 2,
        "unique_users": 1,
        "watch_min": 0.1
      },
      {
        "lang": "Marathi",
        "tunes": 1,
        "unique_users": 1,
        "watch_min": 0.1
      },
      {
        "lang": "English",
        "tunes": 2,
        "unique_users": 1,
        "watch_min": 0.1
      },
      {
        "lang": "Bhojpuri",
        "tunes": 2,
        "unique_users": 2,
        "watch_min": 0.1
      }
    ],
    "hourlyTrend": [
      {
        "hour": "2026-07-21 20:00",
        "users": 5,
        "tunes": 19
      }
    ],
    "dailyTrend": [
      {
        "day": "2026-07-21",
        "users": 5,
        "tunes": 19,
        "watch_min": 1.6
      }
    ],
    "deviceBreakdown": [
      {
        "device": "mobile",
        "users": 5
      }
    ],
    "funnel": {
      "opens": 5,
      "playback": 4,
      "engaged": 0
    },
    "retention": {
      "new_users": 3,
      "returning_users": 2
    },
    "errorBoard": [
      {
        "ch": 4,
        "name": "Epic TV",
        "cat": "Entertainment",
        "errors": 1,
        "starts": 0
      },
      {
        "ch": 10,
        "name": "History TV18 HD",
        "cat": "Entertainment",
        "errors": 1,
        "starts": 0
      },
      {
        "ch": 12,
        "name": "Abzy Movies",
        "cat": "Entertainment",
        "errors": 1,
        "starts": 0
      },
      {
        "ch": 15,
        "name": "NDTV Good Times",
        "cat": "Entertainment",
        "errors": 1,
        "starts": 0
      },
      {
        "ch": 16,
        "name": "Travelxp HD",
        "cat": "Entertainment",
        "errors": 1,
        "starts": 0
      }
    ],
    "perf": {
      "avg_ttff_ms": 2017,
      "samples": 12
    },
    "netBreakdown": [
      {
        "net": "unknown",
        "starts": 9,
        "avg_ttff_ms": 1109
      },
      {
        "net": "4g",
        "starts": 3,
        "avg_ttff_ms": 4744
      }
    ],
    "engagement": {
      "sessions": 5,
      "avg_channels": 3.8,
      "avg_session_sec": 20,
      "bounce_pct": 60,
      "zap_pct": 68.4
    },
    "survey": {
      "very": null,
      "somewhat": null,
      "not_disappointed": null,
      "responses": 0
    }
  }
}
