{
  "fetched_at": "2026-07-19T12:01:32Z",
  "data": {
    "period": "1h",
    "liveNow": 3,
    "overview": {
      "unique_users": 28,
      "total_tunes": 79,
      "total_watch_min": 126.2,
      "avg_duration_sec": 88.1
    },
    "channelLeaderboard": [
      {
        "ch": 118,
        "name": "Goldmines",
        "cat": "Movies",
        "lang": "Hindi",
        "tunes": 7,
        "unique_users": 7,
        "watch_min": 55.6
      },
      {
        "ch": 2,
        "name": "Dangal TV",
        "cat": "Entertainment",
        "lang": "Hindi",
        "tunes": 2,
        "unique_users": 2,
        "watch_min": 14.4
      },
      {
        "ch": 75,
        "name": "Alankar TV",
        "cat": "Movies",
        "lang": "Hindi",
        "tunes": 1,
        "unique_users": 1,
        "watch_min": 3.7
      },
      {
        "ch": 226,
        "name": "Times Now Navbharat",
        "cat": "News",
        "lang": "Hindi",
        "tunes": 8,
        "unique_users": 7,
        "watch_min": 2.4
      },
      {
        "ch": 24,
        "name": "Bhojpuri Cinema",
        "cat": "Movies",
        "lang": "Bhojpuri",
        "tunes": 5,
        "unique_users": 5,
        "watch_min": 1.2
      },
      {
        "ch": 84,
        "name": "B4U Music",
        "cat": "Music",
        "lang": "Hindi",
        "tunes": 3,
        "unique_users": 2,
        "watch_min": 1.1
      },
      {
        "ch": 148,
        "name": "Maha Movie",
        "cat": "Movies",
        "lang": "Hindi",
        "tunes": 1,
        "unique_users": 1,
        "watch_min": 0.8
      },
      {
        "ch": 216,
        "name": "Studio One +",
        "cat": "Movies",
        "lang": "Hindi",
        "tunes": 3,
        "unique_users": 3,
        "watch_min": 0.7
      },
      {
        "ch": 27,
        "name": "9XM",
        "cat": "Music",
        "lang": "Hindi",
        "tunes": 4,
        "unique_users": 2,
        "watch_min": 0.7
      },
      {
        "ch": 210,
        "name": "Stingray Classic Rock",
        "cat": "Music",
        "lang": "English",
        "tunes": 4,
        "unique_users": 2,
        "watch_min": 0.6
      },
      {
        "ch": 34,
        "name": "PTC Music",
        "cat": "Music",
        "lang": "Punjabi",
        "tunes": 3,
        "unique_users": 2,
        "watch_min": 0.4
      },
      {
        "ch": 204,
        "name": "Shalom",
        "cat": "Devotional",
        "lang": "Hindi",
        "tunes": 1,
        "unique_users": 1,
        "watch_min": 0.3
      },
      {
        "ch": 32,
        "name": "B4U Bhojpuri",
        "cat": "Music",
        "lang": "Bhojpuri",
        "tunes": 4,
        "unique_users": 3,
        "watch_min": 0.3
      },
      {
        "ch": 30,
        "name": "9X Tashan",
        "cat": "Music",
        "lang": "Hindi",
        "tunes": 4,
        "unique_users": 4,
        "watch_min": 0.3
      },
      {
        "ch": 251,
        "name": "Zoom",
        "cat": "Music",
        "lang": "Hindi",
        "tunes": 2,
        "unique_users": 2,
        "watch_min": 0.2
      },
      {
        "ch": 249,
        "name": "Zee Uttar Pradesh/Uttarakhand",
        "cat": "News",
        "lang": "Hindi",
        "tunes": 1,
        "unique_users": 1,
        "watch_min": 0.1
      },
      {
        "ch": 235,
        "name": "Vedic",
        "cat": "Devotional",
        "lang": "Hindi",
        "tunes": 1,
        "unique_users": 1,
        "watch_min": 0.1
      },
      {
        "ch": 173,
        "name": "Peace TV Urdu",
        "cat": "Devotional",
        "lang": "Urdu",
        "tunes": 1,
        "unique_users": 1,
        "watch_min": 0.1
      },
      {
        "ch": 160,
        "name": "NDTV Rajasthan",
        "cat": "News",
        "lang": "Hindi",
        "tunes": 1,
        "unique_users": 1,
        "watch_min": 0.1
      },
      {
        "ch": 100,
        "name": "DD India",
        "cat": "DD",
        "lang": "Hindi",
        "tunes": 1,
        "unique_users": 1,
        "watch_min": 0.1
      },
      {
        "ch": 79,
        "name": "Angel TV",
        "cat": "Devotional",
        "lang": "Hindi",
        "tunes": 2,
        "unique_users": 1,
        "watch_min": 0.1
      },
      {
        "ch": 55,
        "name": "Zee Business",
        "cat": "Business",
        "lang": "Hindi",
        "tunes": 2,
        "unique_users": 1,
        "watch_min": 0.1
      },
      {
        "ch": 41,
        "name": "ABP News",
        "cat": "News",
        "lang": "Hindi",
        "tunes": 2,
        "unique_users": 1,
        "watch_min": 0.1
      },
      {
        "ch": 40,
        "name": "Aaj Tak HD",
        "cat": "News",
        "lang": "Hindi",
        "tunes": 2,
        "unique_users": 1,
        "watch_min": 0.1
      },
      {
        "ch": 37,
        "name": "Punjabi Hits",
        "cat": "Music",
        "lang": "Punjabi",
        "tunes": 1,
        "unique_users": 1,
        "watch_min": 0.1
      },
      {
        "ch": 29,
        "name": "9X Jhakaas",
        "cat": "Music",
        "lang": "Hindi",
        "tunes": 2,
        "unique_users": 2,
        "watch_min": 0.1
      },
      {
        "ch": 18,
        "name": "Desi Channel",
        "cat": "Entertainment",
        "lang": "Hindi",
        "tunes": 1,
        "unique_users": 1,
        "watch_min": 0.1
      },
      {
        "ch": 10,
        "name": "History TV18 HD",
        "cat": "Entertainment",
        "lang": "Hindi",
        "tunes": 1,
        "unique_users": 1,
        "watch_min": 0.1
      },
      {
        "ch": 7,
        "name": "Zee Horror Nights",
        "cat": "Entertainment",
        "lang": "Hindi",
        "tunes": 1,
        "unique_users": 1,
        "watch_min": 0.1
      },
      {
        "ch": 147,
        "name": "Living India News",
        "cat": "News",
        "lang": "Punjabi",
        "tunes": 1,
        "unique_users": 1,
        "watch_min": 0
      }
    ],
    "categoryBreakdown": [
      {
        "cat": "Movies",
        "tunes": 17,
        "unique_users": 8,
        "watch_min": 62
      },
      {
        "cat": "Entertainment",
        "tunes": 7,
        "unique_users": 3,
        "watch_min": 14.8
      },
      {
        "cat": "Music",
        "tunes": 27,
        "unique_users": 7,
        "watch_min": 3.6
      },
      {
        "cat": "News",
        "tunes": 19,
        "unique_users": 7,
        "watch_min": 2.8
      },
      {
        "cat": "Devotional",
        "tunes": 5,
        "unique_users": 3,
        "watch_min": 0.6
      },
      {
        "cat": "DD",
        "tunes": 2,
        "unique_users": 1,
        "watch_min": 0.1
      },
      {
        "cat": "Business",
        "tunes": 2,
        "unique_users": 1,
        "watch_min": 0.1
      }
    ],
    "languageBreakdown": [
      {
        "lang": "Hindi",
        "tunes": 59,
        "unique_users": 19,
        "watch_min": 81.4
      },
      {
        "lang": "Bhojpuri",
        "tunes": 9,
        "unique_users": 8,
        "watch_min": 1.5
      },
      {
        "lang": "English",
        "tunes": 5,
        "unique_users": 3,
        "watch_min": 0.6
      },
      {
        "lang": "Punjabi",
        "tunes": 5,
        "unique_users": 4,
        "watch_min": 0.4
      },
      {
        "lang": "Urdu",
        "tunes": 1,
        "unique_users": 1,
        "watch_min": 0.1
      }
    ],
    "hourlyTrend": [
      {
        "hour": "2026-07-19 11:00",
        "users": 26,
        "tunes": 76
      },
      {
        "hour": "2026-07-19 12:00",
        "users": 2,
        "tunes": 3
      }
    ],
    "dailyTrend": [
      {
        "day": "2026-07-19",
        "users": 28,
        "tunes": 79,
        "watch_min": 126.2
      }
    ],
    "deviceBreakdown": [
      {
        "device": "mobile",
        "users": 24
      },
      {
        "device": "desktop",
        "users": 2
      }
    ],
    "funnel": {
      "opens": 23,
      "playback": 17,
      "engaged": 4
    },
    "retention": {
      "new_users": 14,
      "returning_users": 11
    },
    "errorBoard": [
      {
        "ch": 4,
        "name": "Epic TV",
        "cat": "Entertainment",
        "errors": 1,
        "starts": 0
      },
      {
        "ch": 10,
        "name": "History TV18 HD",
        "cat": "Entertainment",
        "errors": 1,
        "starts": 0
      },
      {
        "ch": 235,
        "name": "Vedic",
        "cat": "Devotional",
        "errors": 1,
        "starts": 0
      }
    ],
    "perf": {
      "avg_ttff_ms": 8149,
      "samples": 56
    },
    "netBreakdown": [
      {
        "net": "4g",
        "starts": 50,
        "avg_ttff_ms": 8507
      },
      {
        "net": "3g",
        "starts": 5,
        "avg_ttff_ms": 5537
      },
      {
        "net": "unknown",
        "starts": 1,
        "avg_ttff_ms": 3312
      }
    ],
    "engagement": {
      "sessions": 28,
      "avg_channels": 2.4,
      "avg_session_sec": 70,
      "bounce_pct": 60.7,
      "zap_pct": 48.1
    },
    "survey": {
      "very": null,
      "somewhat": null,
      "not_disappointed": null,
      "responses": 0
    }
  }
}
