{
  "fetched_at": "2026-07-15T12:17:00Z",
  "data": {
    "period": "7d",
    "liveNow": 3,
    "overview": {
      "unique_users": 3703,
      "total_tunes": 18725,
      "total_watch_min": 359749.5,
      "avg_duration_sec": 1019.9
    },
    "channelLeaderboard": [
      {
        "ch": 2,
        "name": "Dangal TV",
        "cat": "Entertainment",
        "lang": "Hindi",
        "tunes": 1995,
        "unique_users": 1689,
        "watch_min": 2051.2
      },
      {
        "ch": 226,
        "name": "Times Now Navbharat",
        "cat": "News",
        "lang": "Hindi",
        "tunes": 77,
        "unique_users": 65,
        "watch_min": 1166.5
      },
      {
        "ch": 45,
        "name": "Zee Bharat",
        "cat": "News",
        "lang": "Hindi",
        "tunes": 125,
        "unique_users": 105,
        "watch_min": 935.9
      },
      {
        "ch": 24,
        "name": "Bhojpuri Cinema",
        "cat": "Movies",
        "lang": "Bhojpuri",
        "tunes": 466,
        "unique_users": 312,
        "watch_min": 932.5
      },
      {
        "ch": 7,
        "name": "Zee Horror Nights",
        "cat": "Entertainment",
        "lang": "Hindi",
        "tunes": 409,
        "unique_users": 325,
        "watch_min": 396.8
      },
      {
        "ch": 82,
        "name": "Arputhar Yesu TV",
        "cat": "Devotional",
        "lang": "Hindi",
        "tunes": 34,
        "unique_users": 31,
        "watch_min": 376.5
      },
      {
        "ch": 9,
        "name": "Zee South Flix",
        "cat": "Entertainment",
        "lang": "Hindi",
        "tunes": 294,
        "unique_users": 240,
        "watch_min": 338.9
      },
      {
        "ch": 40,
        "name": "Aaj Tak HD",
        "cat": "News",
        "lang": "Hindi",
        "tunes": 342,
        "unique_users": 275,
        "watch_min": 334
      },
      {
        "ch": 3,
        "name": "Dangal 2",
        "cat": "Entertainment",
        "lang": "Hindi",
        "tunes": 607,
        "unique_users": 497,
        "watch_min": 327.4
      },
      {
        "ch": 118,
        "name": "Goldmines",
        "cat": "Movies",
        "lang": "Hindi",
        "tunes": 356,
        "unique_users": 264,
        "watch_min": 319.4
      },
      {
        "ch": 119,
        "name": "Goldmines 2",
        "cat": "Movies",
        "lang": "Hindi",
        "tunes": 214,
        "unique_users": 159,
        "watch_min": 313.6
      },
      {
        "ch": 47,
        "name": "Sudarshan News",
        "cat": "News",
        "lang": "Hindi",
        "tunes": 66,
        "unique_users": 59,
        "watch_min": 295.8
      },
      {
        "ch": 241,
        "name": "YRF Music",
        "cat": "Music",
        "lang": "Hindi",
        "tunes": 89,
        "unique_users": 64,
        "watch_min": 258.8
      },
      {
        "ch": 8,
        "name": "Zee Cine Classic",
        "cat": "Entertainment",
        "lang": "Hindi",
        "tunes": 454,
        "unique_users": 343,
        "watch_min": 203.6
      },
      {
        "ch": 5,
        "name": "Zee Comedy Nation",
        "cat": "Entertainment",
        "lang": "Hindi",
        "tunes": 510,
        "unique_users": 397,
        "watch_min": 186.2
      },
      {
        "ch": 194,
        "name": "Sangeet Marathi",
        "cat": "Music",
        "lang": "Marathi",
        "tunes": 56,
        "unique_users": 46,
        "watch_min": 153.8
      },
      {
        "ch": 4,
        "name": "Epic TV",
        "cat": "Entertainment",
        "lang": "Hindi",
        "tunes": 454,
        "unique_users": 364,
        "watch_min": 153.7
      },
      {
        "ch": 41,
        "name": "ABP News",
        "cat": "News",
        "lang": "Hindi",
        "tunes": 164,
        "unique_users": 135,
        "watch_min": 153.5
      },
      {
        "ch": 30,
        "name": "9X Tashan",
        "cat": "Music",
        "lang": "Hindi",
        "tunes": 328,
        "unique_users": 248,
        "watch_min": 134.9
      },
      {
        "ch": 6,
        "name": "Zee Dil Se",
        "cat": "Entertainment",
        "lang": "Hindi",
        "tunes": 350,
        "unique_users": 276,
        "watch_min": 125.5
      },
      {
        "ch": 27,
        "name": "9XM",
        "cat": "Music",
        "lang": "Hindi",
        "tunes": 278,
        "unique_users": 197,
        "watch_min": 108.8
      },
      {
        "ch": 17,
        "name": "Shemaroo Josh",
        "cat": "Entertainment",
        "lang": "Hindi",
        "tunes": 362,
        "unique_users": 263,
        "watch_min": 105.5
      },
      {
        "ch": 51,
        "name": "RT India",
        "cat": "News",
        "lang": "English",
        "tunes": 48,
        "unique_users": 34,
        "watch_min": 99.1
      },
      {
        "ch": 154,
        "name": "MNTV",
        "cat": "Entertainment",
        "lang": "Hindi",
        "tunes": 60,
        "unique_users": 29,
        "watch_min": 89.2
      },
      {
        "ch": 21,
        "name": "Travelxp 4K",
        "cat": "Entertainment",
        "lang": "English",
        "tunes": 209,
        "unique_users": 169,
        "watch_min": 83.7
      },
      {
        "ch": 46,
        "name": "News 24",
        "cat": "News",
        "lang": "Hindi",
        "tunes": 97,
        "unique_users": 85,
        "watch_min": 81.7
      },
      {
        "ch": 43,
        "name": "India TV",
        "cat": "News",
        "lang": "Hindi",
        "tunes": 172,
        "unique_users": 146,
        "watch_min": 79.9
      },
      {
        "ch": 73,
        "name": "ABP News",
        "cat": "News",
        "lang": "Hindi",
        "tunes": 88,
        "unique_users": 77,
        "watch_min": 71.9
      },
      {
        "ch": 39,
        "name": "Steelbird Music",
        "cat": "Music",
        "lang": "Hindi",
        "tunes": 190,
        "unique_users": 137,
        "watch_min": 64.4
      },
      {
        "ch": 18,
        "name": "Desi Channel",
        "cat": "Entertainment",
        "lang": "Hindi",
        "tunes": 290,
        "unique_users": 220,
        "watch_min": 63.4
      }
    ],
    "categoryBreakdown": [
      {
        "cat": "Entertainment",
        "tunes": 8133,
        "unique_users": 2315,
        "watch_min": 4498.1
      },
      {
        "cat": "News",
        "tunes": 3446,
        "unique_users": 733,
        "watch_min": 3672.8
      },
      {
        "cat": "Movies",
        "tunes": 1930,
        "unique_users": 691,
        "watch_min": 1687.3
      },
      {
        "cat": "Music",
        "tunes": 2747,
        "unique_users": 687,
        "watch_min": 1117
      },
      {
        "cat": "Devotional",
        "tunes": 1160,
        "unique_users": 353,
        "watch_min": 521.4
      },
      {
        "cat": "DD",
        "tunes": 409,
        "unique_users": 152,
        "watch_min": 86.5
      },
      {
        "cat": "Undefined",
        "tunes": 204,
        "unique_users": 105,
        "watch_min": 57.3
      },
      {
        "cat": "Education",
        "tunes": 136,
        "unique_users": 98,
        "watch_min": 20.6
      },
      {
        "cat": "Business",
        "tunes": 92,
        "unique_users": 82,
        "watch_min": 14.3
      },
      {
        "cat": "Sports",
        "tunes": 58,
        "unique_users": 37,
        "watch_min": 12.3
      },
      {
        "cat": "Kids",
        "tunes": 66,
        "unique_users": 56,
        "watch_min": 11.5
      },
      {
        "cat": "Culture",
        "tunes": 89,
        "unique_users": 73,
        "watch_min": 10.7
      },
      {
        "cat": "Animation",
        "tunes": 28,
        "unique_users": 21,
        "watch_min": 10.7
      },
      {
        "cat": "Classic",
        "tunes": 70,
        "unique_users": 57,
        "watch_min": 8
      },
      {
        "cat": "Family",
        "tunes": 42,
        "unique_users": 23,
        "watch_min": 7
      },
      {
        "cat": "Science",
        "tunes": 17,
        "unique_users": 16,
        "watch_min": 5.7
      },
      {
        "cat": "Weather",
        "tunes": 22,
        "unique_users": 20,
        "watch_min": 3.1
      },
      {
        "cat": "Legislative",
        "tunes": 37,
        "unique_users": 17,
        "watch_min": 3
      },
      {
        "cat": "Documentary",
        "tunes": 18,
        "unique_users": 16,
        "watch_min": 2.3
      },
      {
        "cat": "Lifestyle",
        "tunes": 21,
        "unique_users": 18,
        "watch_min": 1.7
      }
    ],
    "languageBreakdown": [
      {
        "lang": "Hindi",
        "tunes": 15109,
        "unique_users": 2961,
        "watch_min": 9941.4
      },
      {
        "lang": "Bhojpuri",
        "tunes": 825,
        "unique_users": 473,
        "watch_min": 986.9
      },
      {
        "lang": "English",
        "tunes": 1234,
        "unique_users": 509,
        "watch_min": 418.4
      },
      {
        "lang": "Punjabi",
        "tunes": 1046,
        "unique_users": 479,
        "watch_min": 197.2
      },
      {
        "lang": "Marathi",
        "tunes": 407,
        "unique_users": 241,
        "watch_min": 196.4
      },
      {
        "lang": "Urdu",
        "tunes": 104,
        "unique_users": 75,
        "watch_min": 10.9
      }
    ],
    "hourlyTrend": [
      {
        "hour": "2026-07-08 12:00",
        "users": 24,
        "tunes": 148
      },
      {
        "hour": "2026-07-08 13:00",
        "users": 24,
        "tunes": 156
      },
      {
        "hour": "2026-07-08 14:00",
        "users": 27,
        "tunes": 151
      },
      {
        "hour": "2026-07-08 15:00",
        "users": 44,
        "tunes": 176
      },
      {
        "hour": "2026-07-08 16:00",
        "users": 70,
        "tunes": 463
      },
      {
        "hour": "2026-07-08 17:00",
        "users": 46,
        "tunes": 392
      },
      {
        "hour": "2026-07-08 18:00",
        "users": 24,
        "tunes": 94
      },
      {
        "hour": "2026-07-08 19:00",
        "users": 16,
        "tunes": 74
      },
      {
        "hour": "2026-07-08 20:00",
        "users": 8,
        "tunes": 13
      },
      {
        "hour": "2026-07-08 21:00",
        "users": 11,
        "tunes": 12
      },
      {
        "hour": "2026-07-08 22:00",
        "users": 7,
        "tunes": 115
      },
      {
        "hour": "2026-07-08 23:00",
        "users": 6,
        "tunes": 52
      },
      {
        "hour": "2026-07-09 00:00",
        "users": 4,
        "tunes": 76
      },
      {
        "hour": "2026-07-09 01:00",
        "users": 12,
        "tunes": 117
      },
      {
        "hour": "2026-07-09 02:00",
        "users": 23,
        "tunes": 148
      },
      {
        "hour": "2026-07-09 03:00",
        "users": 18,
        "tunes": 103
      },
      {
        "hour": "2026-07-09 04:00",
        "users": 33,
        "tunes": 115
      },
      {
        "hour": "2026-07-09 05:00",
        "users": 37,
        "tunes": 200
      },
      {
        "hour": "2026-07-09 06:00",
        "users": 31,
        "tunes": 78
      },
      {
        "hour": "2026-07-09 07:00",
        "users": 36,
        "tunes": 98
      },
      {
        "hour": "2026-07-09 08:00",
        "users": 36,
        "tunes": 102
      },
      {
        "hour": "2026-07-09 09:00",
        "users": 32,
        "tunes": 225
      },
      {
        "hour": "2026-07-09 10:00",
        "users": 35,
        "tunes": 137
      },
      {
        "hour": "2026-07-09 11:00",
        "users": 48,
        "tunes": 204
      },
      {
        "hour": "2026-07-09 12:00",
        "users": 43,
        "tunes": 269
      },
      {
        "hour": "2026-07-09 13:00",
        "users": 29,
        "tunes": 90
      },
      {
        "hour": "2026-07-09 14:00",
        "users": 34,
        "tunes": 288
      },
      {
        "hour": "2026-07-09 15:00",
        "users": 39,
        "tunes": 216
      },
      {
        "hour": "2026-07-09 16:00",
        "users": 49,
        "tunes": 147
      },
      {
        "hour": "2026-07-09 17:00",
        "users": 41,
        "tunes": 142
      },
      {
        "hour": "2026-07-09 18:00",
        "users": 30,
        "tunes": 179
      },
      {
        "hour": "2026-07-09 19:00",
        "users": 16,
        "tunes": 29
      },
      {
        "hour": "2026-07-09 20:00",
        "users": 9,
        "tunes": 31
      },
      {
        "hour": "2026-07-09 21:00",
        "users": 7,
        "tunes": 9
      },
      {
        "hour": "2026-07-09 23:00",
        "users": 4,
        "tunes": 11
      },
      {
        "hour": "2026-07-10 00:00",
        "users": 7,
        "tunes": 68
      },
      {
        "hour": "2026-07-10 01:00",
        "users": 5,
        "tunes": 27
      },
      {
        "hour": "2026-07-10 02:00",
        "users": 21,
        "tunes": 49
      },
      {
        "hour": "2026-07-10 03:00",
        "users": 25,
        "tunes": 123
      },
      {
        "hour": "2026-07-10 04:00",
        "users": 17,
        "tunes": 77
      },
      {
        "hour": "2026-07-10 05:00",
        "users": 28,
        "tunes": 209
      },
      {
        "hour": "2026-07-10 06:00",
        "users": 20,
        "tunes": 239
      },
      {
        "hour": "2026-07-10 07:00",
        "users": 32,
        "tunes": 306
      },
      {
        "hour": "2026-07-10 08:00",
        "users": 32,
        "tunes": 217
      },
      {
        "hour": "2026-07-10 09:00",
        "users": 28,
        "tunes": 142
      },
      {
        "hour": "2026-07-10 10:00",
        "users": 15,
        "tunes": 39
      },
      {
        "hour": "2026-07-10 11:00",
        "users": 35,
        "tunes": 166
      },
      {
        "hour": "2026-07-10 12:00",
        "users": 31,
        "tunes": 166
      },
      {
        "hour": "2026-07-10 13:00",
        "users": 23,
        "tunes": 81
      },
      {
        "hour": "2026-07-10 14:00",
        "users": 33,
        "tunes": 75
      },
      {
        "hour": "2026-07-10 15:00",
        "users": 27,
        "tunes": 72
      },
      {
        "hour": "2026-07-10 16:00",
        "users": 47,
        "tunes": 291
      },
      {
        "hour": "2026-07-10 17:00",
        "users": 42,
        "tunes": 214
      },
      {
        "hour": "2026-07-10 18:00",
        "users": 30,
        "tunes": 122
      },
      {
        "hour": "2026-07-10 19:00",
        "users": 19,
        "tunes": 98
      },
      {
        "hour": "2026-07-10 20:00",
        "users": 13,
        "tunes": 27
      },
      {
        "hour": "2026-07-10 21:00",
        "users": 5,
        "tunes": 7
      },
      {
        "hour": "2026-07-10 22:00",
        "users": 3,
        "tunes": 3
      },
      {
        "hour": "2026-07-10 23:00",
        "users": 3,
        "tunes": 5
      },
      {
        "hour": "2026-07-11 00:00",
        "users": 4,
        "tunes": 2
      },
      {
        "hour": "2026-07-11 01:00",
        "users": 6,
        "tunes": 57
      },
      {
        "hour": "2026-07-11 02:00",
        "users": 17,
        "tunes": 54
      },
      {
        "hour": "2026-07-11 03:00",
        "users": 25,
        "tunes": 123
      },
      {
        "hour": "2026-07-11 04:00",
        "users": 17,
        "tunes": 84
      },
      {
        "hour": "2026-07-11 05:00",
        "users": 27,
        "tunes": 179
      },
      {
        "hour": "2026-07-11 06:00",
        "users": 29,
        "tunes": 95
      },
      {
        "hour": "2026-07-11 07:00",
        "users": 19,
        "tunes": 52
      },
      {
        "hour": "2026-07-11 08:00",
        "users": 13,
        "tunes": 41
      },
      {
        "hour": "2026-07-11 09:00",
        "users": 22,
        "tunes": 52
      },
      {
        "hour": "2026-07-11 10:00",
        "users": 16,
        "tunes": 81
      },
      {
        "hour": "2026-07-11 11:00",
        "users": 29,
        "tunes": 100
      },
      {
        "hour": "2026-07-11 12:00",
        "users": 17,
        "tunes": 32
      },
      {
        "hour": "2026-07-11 13:00",
        "users": 28,
        "tunes": 79
      },
      {
        "hour": "2026-07-11 14:00",
        "users": 28,
        "tunes": 71
      },
      {
        "hour": "2026-07-11 15:00",
        "users": 25,
        "tunes": 94
      },
      {
        "hour": "2026-07-11 16:00",
        "users": 39,
        "tunes": 188
      },
      {
        "hour": "2026-07-11 17:00",
        "users": 69,
        "tunes": 282
      },
      {
        "hour": "2026-07-11 18:00",
        "users": 25,
        "tunes": 69
      },
      {
        "hour": "2026-07-11 19:00",
        "users": 38,
        "tunes": 99
      },
      {
        "hour": "2026-07-11 20:00",
        "users": 13,
        "tunes": 108
      },
      {
        "hour": "2026-07-11 21:00",
        "users": 8,
        "tunes": 76
      },
      {
        "hour": "2026-07-11 22:00",
        "users": 2,
        "tunes": 2
      },
      {
        "hour": "2026-07-11 23:00",
        "users": 7,
        "tunes": 21
      },
      {
        "hour": "2026-07-12 00:00",
        "users": 7,
        "tunes": 14
      },
      {
        "hour": "2026-07-12 01:00",
        "users": 11,
        "tunes": 25
      },
      {
        "hour": "2026-07-12 02:00",
        "users": 12,
        "tunes": 25
      },
      {
        "hour": "2026-07-12 03:00",
        "users": 16,
        "tunes": 82
      },
      {
        "hour": "2026-07-12 04:00",
        "users": 29,
        "tunes": 93
      },
      {
        "hour": "2026-07-12 05:00",
        "users": 35,
        "tunes": 174
      },
      {
        "hour": "2026-07-12 06:00",
        "users": 44,
        "tunes": 208
      },
      {
        "hour": "2026-07-12 07:00",
        "users": 34,
        "tunes": 370
      },
      {
        "hour": "2026-07-12 08:00",
        "users": 29,
        "tunes": 193
      },
      {
        "hour": "2026-07-12 09:00",
        "users": 42,
        "tunes": 270
      },
      {
        "hour": "2026-07-12 10:00",
        "users": 30,
        "tunes": 129
      },
      {
        "hour": "2026-07-12 11:00",
        "users": 36,
        "tunes": 150
      },
      {
        "hour": "2026-07-12 12:00",
        "users": 27,
        "tunes": 102
      },
      {
        "hour": "2026-07-12 13:00",
        "users": 32,
        "tunes": 227
      },
      {
        "hour": "2026-07-12 14:00",
        "users": 30,
        "tunes": 139
      },
      {
        "hour": "2026-07-12 15:00",
        "users": 33,
        "tunes": 145
      },
      {
        "hour": "2026-07-12 16:00",
        "users": 47,
        "tunes": 284
      },
      {
        "hour": "2026-07-12 17:00",
        "users": 52,
        "tunes": 230
      },
      {
        "hour": "2026-07-12 18:00",
        "users": 44,
        "tunes": 183
      },
      {
        "hour": "2026-07-12 19:00",
        "users": 22,
        "tunes": 104
      },
      {
        "hour": "2026-07-12 20:00",
        "users": 7,
        "tunes": 14
      },
      {
        "hour": "2026-07-12 21:00",
        "users": 6,
        "tunes": 21
      },
      {
        "hour": "2026-07-12 22:00",
        "users": 3,
        "tunes": 6
      },
      {
        "hour": "2026-07-12 23:00",
        "users": 1,
        "tunes": 2
      },
      {
        "hour": "2026-07-13 00:00",
        "users": 2,
        "tunes": 2
      },
      {
        "hour": "2026-07-13 01:00",
        "users": 6,
        "tunes": 32
      },
      {
        "hour": "2026-07-13 02:00",
        "users": 7,
        "tunes": 12
      },
      {
        "hour": "2026-07-13 03:00",
        "users": 11,
        "tunes": 32
      },
      {
        "hour": "2026-07-13 04:00",
        "users": 24,
        "tunes": 135
      },
      {
        "hour": "2026-07-13 05:00",
        "users": 29,
        "tunes": 141
      },
      {
        "hour": "2026-07-13 06:00",
        "users": 29,
        "tunes": 123
      },
      {
        "hour": "2026-07-13 07:00",
        "users": 26,
        "tunes": 209
      },
      {
        "hour": "2026-07-13 08:00",
        "users": 24,
        "tunes": 111
      },
      {
        "hour": "2026-07-13 09:00",
        "users": 19,
        "tunes": 95
      },
      {
        "hour": "2026-07-13 10:00",
        "users": 19,
        "tunes": 137
      },
      {
        "hour": "2026-07-13 11:00",
        "users": 23,
        "tunes": 83
      },
      {
        "hour": "2026-07-13 12:00",
        "users": 23,
        "tunes": 94
      },
      {
        "hour": "2026-07-13 13:00",
        "users": 28,
        "tunes": 200
      },
      {
        "hour": "2026-07-13 14:00",
        "users": 21,
        "tunes": 183
      },
      {
        "hour": "2026-07-13 15:00",
        "users": 39,
        "tunes": 138
      },
      {
        "hour": "2026-07-13 16:00",
        "users": 23,
        "tunes": 90
      },
      {
        "hour": "2026-07-13 17:00",
        "users": 39,
        "tunes": 157
      },
      {
        "hour": "2026-07-13 18:00",
        "users": 36,
        "tunes": 244
      },
      {
        "hour": "2026-07-13 19:00",
        "users": 21,
        "tunes": 184
      },
      {
        "hour": "2026-07-13 20:00",
        "users": 2,
        "tunes": 2
      },
      {
        "hour": "2026-07-13 21:00",
        "users": 6,
        "tunes": 58
      },
      {
        "hour": "2026-07-13 22:00",
        "users": 4,
        "tunes": 17
      },
      {
        "hour": "2026-07-13 23:00",
        "users": 2,
        "tunes": 4
      },
      {
        "hour": "2026-07-14 00:00",
        "users": 3,
        "tunes": 30
      },
      {
        "hour": "2026-07-14 01:00",
        "users": 10,
        "tunes": 6
      },
      {
        "hour": "2026-07-14 02:00",
        "users": 10,
        "tunes": 43
      },
      {
        "hour": "2026-07-14 03:00",
        "users": 17,
        "tunes": 118
      },
      {
        "hour": "2026-07-14 04:00",
        "users": 17,
        "tunes": 67
      },
      {
        "hour": "2026-07-14 05:00",
        "users": 22,
        "tunes": 130
      },
      {
        "hour": "2026-07-14 06:00",
        "users": 22,
        "tunes": 201
      },
      {
        "hour": "2026-07-14 07:00",
        "users": 16,
        "tunes": 65
      },
      {
        "hour": "2026-07-14 08:00",
        "users": 24,
        "tunes": 146
      },
      {
        "hour": "2026-07-14 09:00",
        "users": 34,
        "tunes": 213
      },
      {
        "hour": "2026-07-14 10:00",
        "users": 22,
        "tunes": 60
      },
      {
        "hour": "2026-07-14 11:00",
        "users": 23,
        "tunes": 48
      },
      {
        "hour": "2026-07-14 12:00",
        "users": 15,
        "tunes": 63
      },
      {
        "hour": "2026-07-14 13:00",
        "users": 28,
        "tunes": 112
      },
      {
        "hour": "2026-07-14 14:00",
        "users": 35,
        "tunes": 116
      },
      {
        "hour": "2026-07-14 15:00",
        "users": 32,
        "tunes": 142
      },
      {
        "hour": "2026-07-14 16:00",
        "users": 37,
        "tunes": 256
      },
      {
        "hour": "2026-07-14 17:00",
        "users": 39,
        "tunes": 207
      },
      {
        "hour": "2026-07-14 18:00",
        "users": 39,
        "tunes": 156
      },
      {
        "hour": "2026-07-14 19:00",
        "users": 18,
        "tunes": 60
      },
      {
        "hour": "2026-07-14 20:00",
        "users": 3,
        "tunes": 6
      },
      {
        "hour": "2026-07-14 21:00",
        "users": 11,
        "tunes": 53
      },
      {
        "hour": "2026-07-14 22:00",
        "users": 3,
        "tunes": 28
      },
      {
        "hour": "2026-07-14 23:00",
        "users": 2,
        "tunes": 4
      },
      {
        "hour": "2026-07-15 00:00",
        "users": 2,
        "tunes": 29
      },
      {
        "hour": "2026-07-15 01:00",
        "users": 3,
        "tunes": 8
      },
      {
        "hour": "2026-07-15 02:00",
        "users": 15,
        "tunes": 101
      },
      {
        "hour": "2026-07-15 03:00",
        "users": 16,
        "tunes": 33
      },
      {
        "hour": "2026-07-15 04:00",
        "users": 14,
        "tunes": 53
      },
      {
        "hour": "2026-07-15 05:00",
        "users": 21,
        "tunes": 75
      },
      {
        "hour": "2026-07-15 06:00",
        "users": 34,
        "tunes": 102
      },
      {
        "hour": "2026-07-15 07:00",
        "users": 37,
        "tunes": 288
      },
      {
        "hour": "2026-07-15 08:00",
        "users": 21,
        "tunes": 66
      },
      {
        "hour": "2026-07-15 09:00",
        "users": 21,
        "tunes": 75
      },
      {
        "hour": "2026-07-15 10:00",
        "users": 30,
        "tunes": 125
      },
      {
        "hour": "2026-07-15 11:00",
        "users": 20,
        "tunes": 30
      },
      {
        "hour": "2026-07-15 12:00",
        "users": 8,
        "tunes": 13
      }
    ],
    "dailyTrend": [
      {
        "day": "2026-07-08",
        "users": 295,
        "tunes": 1846,
        "watch_min": 28009.2
      },
      {
        "day": "2026-07-09",
        "users": 630,
        "tunes": 3014,
        "watch_min": 148415.4
      },
      {
        "day": "2026-07-10",
        "users": 521,
        "tunes": 2823,
        "watch_min": 33286.6
      },
      {
        "day": "2026-07-11",
        "users": 507,
        "tunes": 2041,
        "watch_min": 18827.4
      },
      {
        "day": "2026-07-12",
        "users": 604,
        "tunes": 3190,
        "watch_min": 55657.1
      },
      {
        "day": "2026-07-13",
        "users": 447,
        "tunes": 2483,
        "watch_min": 20633.1
      },
      {
        "day": "2026-07-14",
        "users": 464,
        "tunes": 2330,
        "watch_min": 45733.5
      },
      {
        "day": "2026-07-15",
        "users": 239,
        "tunes": 998,
        "watch_min": 9187.2
      }
    ],
    "deviceBreakdown": [
      {
        "device": "mobile",
        "users": 3532
      },
      {
        "device": "desktop",
        "users": 64
      }
    ],
    "funnel": {
      "opens": 2258,
      "playback": 1772,
      "engaged": 303
    },
    "retention": {
      "new_users": 1991,
      "returning_users": 290
    },
    "errorBoard": [
      {
        "ch": 10,
        "name": "History TV18 HD",
        "cat": "Entertainment",
        "errors": 152,
        "starts": 0
      },
      {
        "ch": 16,
        "name": "Travelxp HD",
        "cat": "Entertainment",
        "errors": 140,
        "starts": 0
      },
      {
        "ch": 23,
        "name": "B4U Kadak",
        "cat": "Movies",
        "errors": 139,
        "starts": 0
      },
      {
        "ch": 15,
        "name": "NDTV Good Times",
        "cat": "Entertainment",
        "errors": 138,
        "starts": 0
      },
      {
        "ch": 2,
        "name": "Dangal TV",
        "cat": "Entertainment",
        "errors": 97,
        "starts": 1506
      },
      {
        "ch": 14,
        "name": "Mango TV",
        "cat": "Entertainment",
        "errors": 85,
        "starts": 0
      },
      {
        "ch": 19,
        "name": "Filamchi Bhojpuri",
        "cat": "Entertainment",
        "errors": 79,
        "starts": 10
      },
      {
        "ch": 12,
        "name": "Abzy Movies",
        "cat": "Entertainment",
        "errors": 78,
        "starts": 0
      },
      {
        "ch": 4,
        "name": "Epic TV",
        "cat": "Entertainment",
        "errors": 76,
        "starts": 170
      },
      {
        "ch": 13,
        "name": "Abzy Dhakad",
        "cat": "Entertainment",
        "errors": 69,
        "starts": 0
      },
      {
        "ch": 28,
        "name": "9X Jalwa",
        "cat": "Music",
        "errors": 51,
        "starts": 0
      },
      {
        "ch": 17,
        "name": "Shemaroo Josh",
        "cat": "Entertainment",
        "errors": 38,
        "starts": 185
      },
      {
        "ch": 52,
        "name": "Bharat24",
        "cat": "News",
        "errors": 36,
        "starts": 0
      },
      {
        "ch": 7,
        "name": "Zee Horror Nights",
        "cat": "Entertainment",
        "errors": 33,
        "starts": 242
      },
      {
        "ch": 125,
        "name": "Hare Krsna TV",
        "cat": "Devotional",
        "errors": 26,
        "starts": 0
      },
      {
        "ch": 18,
        "name": "Desi Channel",
        "cat": "Entertainment",
        "errors": 23,
        "starts": 89
      },
      {
        "ch": 5,
        "name": "Zee Comedy Nation",
        "cat": "Entertainment",
        "errors": 21,
        "starts": 340
      },
      {
        "ch": 118,
        "name": "Goldmines",
        "cat": "Movies",
        "errors": 20,
        "starts": 227
      },
      {
        "ch": 40,
        "name": "Aaj Tak HD",
        "cat": "News",
        "errors": 19,
        "starts": 271
      },
      {
        "ch": 8,
        "name": "Zee Cine Classic",
        "cat": "Entertainment",
        "errors": 19,
        "starts": 294
      },
      {
        "ch": 22,
        "name": "B4U Movies",
        "cat": "Movies",
        "errors": 18,
        "starts": 0
      },
      {
        "ch": 184,
        "name": "RC Music",
        "cat": "Music",
        "errors": 18,
        "starts": 0
      },
      {
        "ch": 42,
        "name": "Zee News",
        "cat": "News",
        "errors": 17,
        "starts": 52
      },
      {
        "ch": 21,
        "name": "Travelxp 4K",
        "cat": "Entertainment",
        "errors": 16,
        "starts": 0
      },
      {
        "ch": 119,
        "name": "Goldmines 2",
        "cat": "Movies",
        "errors": 16,
        "starts": 118
      },
      {
        "ch": 27,
        "name": "9XM",
        "cat": "Music",
        "errors": 16,
        "starts": 122
      },
      {
        "ch": 24,
        "name": "Bhojpuri Cinema",
        "cat": "Movies",
        "errors": 16,
        "starts": 347
      },
      {
        "ch": 149,
        "name": "Maha Punjabi",
        "cat": "Entertainment",
        "errors": 15,
        "starts": 50
      },
      {
        "ch": 3,
        "name": "Dangal 2",
        "cat": "Entertainment",
        "errors": 15,
        "starts": 425
      },
      {
        "ch": 128,
        "name": "Hi Dost!",
        "cat": "Entertainment",
        "errors": 14,
        "starts": 45
      },
      {
        "ch": 30,
        "name": "9X Tashan",
        "cat": "Music",
        "errors": 14,
        "starts": 207
      },
      {
        "ch": 32,
        "name": "B4U Bhojpuri",
        "cat": "Music",
        "errors": 13,
        "starts": 64
      },
      {
        "ch": 39,
        "name": "Steelbird Music",
        "cat": "Music",
        "errors": 13,
        "starts": 90
      },
      {
        "ch": 9,
        "name": "Zee South Flix",
        "cat": "Entertainment",
        "errors": 13,
        "starts": 187
      },
      {
        "ch": 47,
        "name": "Sudarshan News",
        "cat": "News",
        "errors": 12,
        "starts": 26
      },
      {
        "ch": 206,
        "name": "Shemaroo TV",
        "cat": "Entertainment",
        "errors": 12,
        "starts": 68
      },
      {
        "ch": 25,
        "name": "ZB Cinema",
        "cat": "Movies",
        "errors": 12,
        "starts": 69
      },
      {
        "ch": 41,
        "name": "ABP News",
        "cat": "News",
        "errors": 12,
        "starts": 109
      },
      {
        "ch": 26,
        "name": "Shemaroo Marathi Bana",
        "cat": "Movies",
        "errors": 11,
        "starts": 94
      },
      {
        "ch": 36,
        "name": "Zoom",
        "cat": "Music",
        "errors": 10,
        "starts": 0
      }
    ],
    "perf": {
      "avg_ttff_ms": 8229,
      "samples": 9771
    },
    "netBreakdown": [
      {
        "net": "4g",
        "starts": 7956,
        "avg_ttff_ms": 7385
      },
      {
        "net": "3g",
        "starts": 938,
        "avg_ttff_ms": 20615
      },
      {
        "net": "unknown",
        "starts": 812,
        "avg_ttff_ms": 2074
      },
      {
        "net": "2g",
        "starts": 37,
        "avg_ttff_ms": 13004
      },
      {
        "net": "slow-2g",
        "starts": 28,
        "avg_ttff_ms": 5345
      }
    ],
    "engagement": {
      "sessions": 3703,
      "avg_channels": 4.1,
      "avg_session_sec": 199,
      "bounce_pct": 45.9,
      "zap_pct": 51.4
    },
    "survey": {
      "very": 32,
      "somewhat": 7,
      "not_disappointed": 2,
      "responses": 41
    }
  }
}
